smartagro/__init__.py
smartagro/cli.py
smartagro/smart.py
smartagro/utils.py
smartagro-0.2.0.dist-info/AUTHORS.rst
smartagro-0.2.0.dist-info/LICENSE
smartagro-0.2.0.dist-info/METADATA
smartagro-0.2.0.dist-info/WHEEL
smartagro-0.2.0.dist-info/entry_points.txt
smartagro-0.2.0.dist-info/top_level.txt
smartagro-0.2.0.dist-info/RECORD
