Metadata-Version: 2.1
Name: smartagro
Version: 0.2.0
Summary: Smart, Iot-enabled greenhouse monitoring and control API
Home-page: https://github.com/chris-kck/smartagro
Author: Kudzai Chris Kateera
Author-email: kckateera@gmail.com
License: GNU General Public License v3
Keywords: smartagro
Platform: UNKNOWN
Classifier: Development Status :: 5 - Production/Stable
Classifier: Intended Audience :: Developers
Classifier: License :: OSI Approved :: GNU General Public License v3 (GPLv3)
Classifier: Natural Language :: English
Classifier: Programming Language :: Python :: 3
Classifier: Programming Language :: Python :: 3.6
Classifier: Programming Language :: Python :: 3.7
Classifier: Programming Language :: Python :: 3.8
Requires-Python: >=3.6
Requires-Dist: Click (>=7.0)
Requires-Dist: paho-mqtt (==1.5.1)
Requires-Dist: spidev
Requires-Dist: sockets
Requires-Dist: RPi.GPIO
Requires-Dist: adafruit-circuitpython-dht
